walkscore/__init__.py
walkscore/__version__.py
walkscore/api.py
walkscore/errors.py
walkscore/http_client.py
walkscore/locationscore.py
walkscore/utilities.py
walkscore_api-1.0.1.dist-info/LICENSE
walkscore_api-1.0.1.dist-info/METADATA
walkscore_api-1.0.1.dist-info/WHEEL
walkscore_api-1.0.1.dist-info/top_level.txt
walkscore_api-1.0.1.dist-info/RECORD
