Metadata-Version: 2.1
Name: walkscore-api
Version: 1.0.1
Summary: Unofficial Python bindings for the WalkScore API
Home-page: https://walkscore-api.readthedocs.io/en/latest
Author: Insight Industry Inc.
Author-email: software@insightindustry.com
License: MIT
Project-URL: Documentation, https://walkscore-api.readthedocs.io/en/latest
Project-URL: Say Thanks!, https://saythanks.io/to/walkscore-api
Project-URL: Bug Reports, https://github.com/insightindustry/walkscore-api/issues
Project-URL: Source, https://github.com/insightindustry/walkscore-api/
Keywords: walkscore binding WalkScore API real estate
Platform: UNKNOWN
Classifier: Development Status :: 4 - Beta
Classifier: Environment :: Web Environment
Classifier: Operating System :: OS Independent
Classifier: Intended Audience :: Developers
Classifier: Topic :: Software Development :: Libraries
Classifier: Topic :: Utilities
Classifier: Topic :: Internet :: WWW/HTTP :: Dynamic Content
Classifier: Topic :: Software Development :: Libraries :: Python Modules
Classifier: Topic :: Database :: Front-Ends
Classifier: License :: OSI Approved :: MIT License
Classifier: Programming Language :: Python :: 3.6
Classifier: Programming Language :: Python :: 3.7
Requires-Python: >2.7, !=3.0.*, !=3.1.*, !=3.2.*, !=3.3.*, <4
Requires-Dist: validator-collection (>=1.3.0)
Requires-Dist: backoff-utils (>=1.0.0)
Provides-Extra: dev
Requires-Dist: check-manifest ; extra == 'dev'
Requires-Dist: sphinx ; extra == 'dev'
Requires-Dist: sphinx-rtd-theme ; extra == 'dev'
Requires-Dist: sphinx-tabs ; extra == 'dev'
Requires-Dist: readme-renderer ; extra == 'dev'
Requires-Dist: restview ; extra == 'dev'
Provides-Extra: test
Requires-Dist: coverage ; extra == 'test'
Requires-Dist: pytest ; extra == 'test'
Requires-Dist: pytest-benchmark ; extra == 'test'
Requires-Dist: pytest-cov ; extra == 'test'
Requires-Dist: tox ; extra == 'test'
Requires-Dist: codecov ; extra == 'test'
